apppy/db/__init__.py
apppy/db/migrations.py
apppy/db/postgres.py
apppy_db-0.23.2.dist-info/METADATA
apppy_db-0.23.2.dist-info/WHEEL
apppy_db-0.23.2.dist-info/RECORD
